danom/__init__.py
danom/_new_type.py
danom/_result.py
danom/_safe.py
danom/_stream.py
danom/_utils.py
danom-0.8.2.dist-info/licenses/LICENSE
danom-0.8.2.dist-info/WHEEL
danom-0.8.2.dist-info/entry_points.txt
danom-0.8.2.dist-info/METADATA
danom-0.8.2.dist-info/RECORD
