Metadata-Version: 2.4
Name: danom
Version: 0.8.2
Summary: Functional streams and monads
Author: ed cuss
Author-email: ed cuss <edcussmusic@gmail.com>
License-Expression: MIT
License-File: LICENSE
Requires-Dist: attrs>=25.4.0
Requires-Python: >=3.12
